{
  "project_info": {
    "project_number": "530201912194",
    "firebase_url": "https://appchat-ee9f5.firebaseio.com",
    "project_id": "appchat-ee9f5",
    "storage_bucket": "appchat-ee9f5.appspot.com"
  },
  "client": [
    {
      "client_info": {
        "mobilesdk_app_id": "1:530201912194:android:659fb29cc14a8b5b",
        "android_client_info": {
          "package_name": "com.example.nguyen.appchat"
        }
      },
      "oauth_client": [
        {
          "client_id": "530201912194-i5421fm5r4rsop7aut0jlpcmcfe4jb9a.apps.googleusercontent.com",
          "client_type": 1,
          "android_info": {
            "package_name": "com.example.nguyen.appchat",
            "certificate_hash": "d060c3d316fed6bc9934cf2f3f4b88f3a79beee5"
          }
        },
        {
          "client_id": "530201912194-u8f7oqv2g39tsuu0n6k9rvb0qa3o6q31.apps.googleusercontent.com",
          "client_type": 3
        }
      ],
      "api_key": [
        {
          "current_key": "AIzaSyCf6xsQvtpppbm-fWTnBuS7YioERpk75ec"
        }
      ],
      "services": {
        "analytics_service": {
          "status": 1
        },
        "appinvite_service": {
          "status": 2,
          "other_platform_oauth_client": [
            {
              "client_id": "530201912194-u8f7oqv2g39tsuu0n6k9rvb0qa3o6q31.apps.googleusercontent.com",
              "client_type": 3
            }
          ]
        },
        "ads_service": {
          "status": 2
        }
      }
    }
  ],
  "configuration_version": "1"
}